mongoengine_pagination/__init__.py
mongoengine_pagination-0.1.5.dist-info/LICENSE.txt
mongoengine_pagination-0.1.5.dist-info/METADATA
mongoengine_pagination-0.1.5.dist-info/WHEEL
mongoengine_pagination-0.1.5.dist-info/top_level.txt
mongoengine_pagination-0.1.5.dist-info/RECORD
